elsapy/__init__.py
elsapy/elsclient.py
elsapy/elsdoc.py
elsapy/elsentity.py
elsapy/elsprofile.py
elsapy/elssearch.py
elsapy/log_util.py
elsapy/utils.py
elsapy-0.5.1.dist-info/LICENSE.md
elsapy-0.5.1.dist-info/METADATA
elsapy-0.5.1.dist-info/WHEEL
elsapy-0.5.1.dist-info/top_level.txt
elsapy-0.5.1.dist-info/RECORD
